{
    "CC D1 DIAGNOSTIC": 0.011390638477379348,
    "CC D2 DIAGNOSTIC": 0.10362947863576673,
    "CC NEW D1 DIAGNOSTIC": 0.011390638477379348,
    "CC T1 DIAGNOSTIC": 0.004517132753780618,
    "CCSD CORRELATION ENERGY": -0.10779363472740233,
    "CCSD OPPOSITE-SPIN CORRELATION ENERGY": -0.08859708585506898,
    "CCSD SAME-SPIN CORRELATION ENERGY": -0.019196548872333172,
    "CCSD TOTAL ENERGY": -460.1518556459542,
    "CURRENT CORRELATION ENERGY": -0.10779363472740233,
    "CURRENT DIPOLE X": 0.0,
    "CURRENT DIPOLE Y": 0.0,
    "CURRENT DIPOLE Z": -1.8130793977971709,
    "CURRENT ENERGY": -460.1518556459542,
    "CURRENT REFERENCE ENERGY": -460.04406201122714,
    "HF TOTAL ENERGY": -460.04406201122714,
    "LCCSD (+LMP2) TOTAL ENERGY": -460.16005343157826,
    "MP2 CORRELATION ENERGY": -0.0989752997817981,
    "MP2 OPPOSITE-SPIN CORRELATION ENERGY": -0.07908892685420812,
    "MP2 SAME-SPIN CORRELATION ENERGY": -0.019886372927589976,
    "MP2 TOTAL ENERGY": -460.1430373110086,
    "NUCLEAR REPULSION ENERGY": 7.938831501980533,
    "ONE-ELECTRON ENERGY": -651.2564354969246,
    "PCM POLARIZATION ENERGY": 0.0,
    "PE ENERGY": 0.0,
    "SCF DIPOLE X": 0.0,
    "SCF DIPOLE Y": 0.0,
    "SCF DIPOLE Z": -1.8130793977971709,
    "SCF ITERATION ENERGY": -460.04406201122714,
    "SCF ITERATIONS": 9.0,
    "SCF TOTAL ENERGY": -460.04406201122714,
    "TWO-ELECTRON ENERGY": 183.27354198371694
}