{
    "CC D1 DIAGNOSTIC": 0.027421199167017032,
    "CC D2 DIAGNOSTIC": 0.09301141417522957,
    "CC NEW D1 DIAGNOSTIC": 0.027421199167017032,
    "CC T1 DIAGNOSTIC": 0.013535660801984064,
    "CCSD CORRELATION ENERGY": -0.17454158185230523,
    "CCSD OPPOSITE-SPIN CORRELATION ENERGY": -0.13895311382282632,
    "CCSD SAME-SPIN CORRELATION ENERGY": -0.035588468029478876,
    "CCSD TOTAL ENERGY": -106.84928802321178,
    "CURRENT CORRELATION ENERGY": -0.17454158185230523,
    "CURRENT DIPOLE X": 0.0,
    "CURRENT DIPOLE Y": 0.0,
    "CURRENT DIPOLE Z": -4.0392157922515235,
    "CURRENT ENERGY": -106.84928802321178,
    "CURRENT REFERENCE ENERGY": -106.67474644135955,
    "HF TOTAL ENERGY": -106.67474644135955,
    "LCCSD (+LMP2) TOTAL ENERGY": -106.94839354212804,
    "MP2 CORRELATION ENERGY": -0.17485166641192013,
    "MP2 OPPOSITE-SPIN CORRELATION ENERGY": -0.13220903231358408,
    "MP2 SAME-SPIN CORRELATION ENERGY": -0.042642634098336046,
    "MP2 TOTAL ENERGY": -106.8495981077714,
    "NUCLEAR REPULSION ENERGY": 14.006251984876403,
    "ONE-ELECTRON ENERGY": -178.0797732871035,
    "PCM POLARIZATION ENERGY": 0.0,
    "PE ENERGY": 0.0,
    "SCF DIPOLE X": 0.0,
    "SCF DIPOLE Y": 0.0,
    "SCF DIPOLE Z": -4.0392157922515235,
    "SCF ITERATION ENERGY": -106.67474644135955,
    "SCF ITERATIONS": 10.0,
    "SCF TOTAL ENERGY": -106.67474644135955,
    "TWO-ELECTRON ENERGY": 57.39877486086756
}