{
    "CC D1 DIAGNOSTIC": 0.009476386647034728,
    "CC D2 DIAGNOSTIC": 0.090260787229725,
    "CC NEW D1 DIAGNOSTIC": 0.009476386647034728,
    "CC T1 DIAGNOSTIC": 0.005275220649197702,
    "CCSD CORRELATION ENERGY": -0.15213526100592986,
    "CCSD OPPOSITE-SPIN CORRELATION ENERGY": -0.12145528266614392,
    "CCSD SAME-SPIN CORRELATION ENERGY": -0.030679978339785974,
    "CCSD TOTAL ENERGY": -100.13171818690931,
    "CURRENT CORRELATION ENERGY": -0.15213526100592986,
    "CURRENT DIPOLE X": 0.0,
    "CURRENT DIPOLE Y": 0.0,
    "CURRENT DIPOLE Z": -2.123218065230108,
    "CURRENT ENERGY": -100.13171818690931,
    "CURRENT REFERENCE ENERGY": -99.97958292590326,
    "HF TOTAL ENERGY": -99.97958292590326,
    "LCCSD (+LMP2) TOTAL ENERGY": -100.1272965378924,
    "MP2 CORRELATION ENERGY": -0.15052479374990838,
    "MP2 OPPOSITE-SPIN CORRELATION ENERGY": -0.11437744606226229,
    "MP2 SAME-SPIN CORRELATION ENERGY": -0.03614734768764609,
    "MP2 TOTAL ENERGY": -100.1301077196533,
    "NUCLEAR REPULSION ENERGY": 6.297384613355282,
    "ONE-ELECTRON ENERGY": -152.41325123076106,
    "PCM POLARIZATION ENERGY": 0.0,
    "PE ENERGY": 0.0,
    "SCF DIPOLE X": 0.0,
    "SCF DIPOLE Y": 0.0,
    "SCF DIPOLE Z": -2.123218065230108,
    "SCF ITERATION ENERGY": -99.97958292590326,
    "SCF ITERATIONS": 9.0,
    "SCF TOTAL ENERGY": -99.97958292590326,
    "TWO-ELECTRON ENERGY": 46.13628369150251
}