{
    "CC D1 DIAGNOSTIC": 0.01391750944688727,
    "CC D2 DIAGNOSTIC": 0.1948818111688406,
    "CC NEW D1 DIAGNOSTIC": 0.01391750944688727,
    "CC T1 DIAGNOSTIC": 0.006121892483701694,
    "CCSD CORRELATION ENERGY": -0.2503184581830845,
    "CCSD OPPOSITE-SPIN CORRELATION ENERGY": -0.20140912402617264,
    "CCSD SAME-SPIN CORRELATION ENERGY": -0.04890933415691176,
    "CCSD TOTAL ENERGY": -149.23783933006254,
    "CURRENT CORRELATION ENERGY": -0.2503184581830845,
    "CURRENT DIPOLE X": 0.0,
    "CURRENT DIPOLE Y": 0.0,
    "CURRENT DIPOLE Z": 0.0,
    "CURRENT ENERGY": -149.23783933006254,
    "CURRENT REFERENCE ENERGY": -148.9875208718795,
    "HF TOTAL ENERGY": -148.9875208718795,
    "LCCSD (+LMP2) TOTAL ENERGY": -149.27259141285248,
    "MP2 CORRELATION ENERGY": -0.2395771586507942,
    "MP2 OPPOSITE-SPIN CORRELATION ENERGY": -0.1843280411584957,
    "MP2 SAME-SPIN CORRELATION ENERGY": -0.05524911749229852,
    "MP2 TOTAL ENERGY": -149.22709803053027,
    "NUCLEAR REPULSION ENERGY": 39.99763178096807,
    "ONE-ELECTRON ENERGY": -282.7939368014804,
    "PCM POLARIZATION ENERGY": 0.0,
    "PE ENERGY": 0.0,
    "SCF DIPOLE X": 0.0,
    "SCF DIPOLE Y": 0.0,
    "SCF DIPOLE Z": 0.0,
    "SCF ITERATION ENERGY": -148.9875208718795,
    "SCF ITERATIONS": 8.0,
    "SCF TOTAL ENERGY": -148.9875208718795,
    "TWO-ELECTRON ENERGY": 93.80878414863284
}